README.md
setup.py
vvm_distributions/Binomialdistribution.py
vvm_distributions/Gaussiandistribution.py
vvm_distributions/Generaldistribution.py
vvm_distributions/__init__.py
vvm_distributions.egg-info/PKG-INFO
vvm_distributions.egg-info/SOURCES.txt
vvm_distributions.egg-info/dependency_links.txt
vvm_distributions.egg-info/not-zip-safe
vvm_distributions.egg-info/top_level.txt